youbike/__init__.py
youbike/__main__.py
youbikepython-0.1.2.dist-info/licenses/LICENSE
youbikepython-0.1.2.dist-info/METADATA
youbikepython-0.1.2.dist-info/WHEEL
youbikepython-0.1.2.dist-info/entry_points.txt
youbikepython-0.1.2.dist-info/top_level.txt
youbikepython-0.1.2.dist-info/RECORD
