Metadata-Version: 2.4
Name: YouBikePython
Version: 0.1.2
Summary: YouBike API for Python
Author-email: AvianJay <avianjayusb@gmail.com>
Requires-Python: >=3.7
License-File: LICENSE
Requires-Dist: requests>2.26.0
Dynamic: license-file
